db0905/__init__.py
db0905/builder.py
db0905/consts.py
db0905/parser.py
db0905/utils.py
demo/__init__.py
demo/dump.py
demo/load.py
tests/__init__.py
tests/test_builder.py
tests/test_parser.py
chenpz-1.0.0.dist-info/LICENSE
chenpz-1.0.0.dist-info/METADATA
chenpz-1.0.0.dist-info/WHEEL
chenpz-1.0.0.dist-info/top_level.txt
chenpz-1.0.0.dist-info/RECORD
