Metadata-Version: 2.1
Name: chenpz
Version: 1.0.0
Summary: A simple xml parse and build library.
Home-page: https://github.com/heronotears/db0905
Author: dbdb
Author-email: <chenpingzhao@gmail.com>
Maintainer: dbdb
License: MIT
Platform: any
Requires-Dist: numpy
